standardizex/__init__.py
standardizex/standardizex_utils.py
standardizex/config/__init__.py
standardizex/config/config_contract.py
standardizex/config/config_factory.py
standardizex/config/v0_json_config.py
standardizex/config/templates/json/v0.json
standardizex/config_reader/__init__.py
standardizex/config_reader/config_reader_contract.py
standardizex/config_reader/config_reader_factory.py
standardizex/config_reader/v0_json_config_reader.py
standardizex/data_standardizer/__init__.py
standardizex/data_standardizer/data_standardizer.py
standardizex/utilities/__init__.py
standardizex/utilities/custom_exceptions.py
standardizex-1.0.0.dist-info/METADATA
standardizex-1.0.0.dist-info/WHEEL
standardizex-1.0.0.dist-info/top_level.txt
standardizex-1.0.0.dist-info/RECORD
