Metadata-Version: 2.1
Name: standardizex
Version: 1.0.0
Summary: Standardizex is a Python package that streamlines data standardization for Delta format tables through a configuration-driven approach.
Home-page: https://github.com/Pallavi-Sinha-12/standardizex
Author: Pallavi Sinha
Author-email: dataaienthusiast128@gmail.com
License: MIT
Classifier: Programming Language :: Python :: 3
Classifier: License :: OSI Approved :: MIT License
Classifier: Operating System :: OS Independent
Requires-Dist: pyspark==3.5.3
Requires-Dist: delta-spark==3.2.1
